setup.py
hdf5lazy/__init__.py
hdf5lazy/core.py
hdf5lazy.egg-info/PKG-INFO
hdf5lazy.egg-info/SOURCES.txt
hdf5lazy.egg-info/dependency_links.txt
hdf5lazy.egg-info/not-zip-safe
hdf5lazy.egg-info/top_level.txt