Metadata-Version: 1.0
Name: hdf5lazy
Version: 0.0.1
Summary: Distributed computing
Home-page: UNKNOWN
Author: Matthew Rocklin
Author-email: mrocklin@gmail.com
License: BSD
Platform: UNKNOWN
